package com.github.minigdx.lua.bytecode

enum class LuaOpcode(val type: LuaOpcodeType) {
    MOVE(LuaOpcodeType.ABC),
    LOADK(LuaOpcodeType.ABx),
    LOADBOOL(LuaOpcodeType.ABC),
    LOADNIL(LuaOpcodeType.ABC),
    GETUPVAL(LuaOpcodeType.ABC),
    GETGLOBAL(LuaOpcodeType.ABx),
    GETTABLE(LuaOpcodeType.ABC),
    SETGLOBAL(LuaOpcodeType.ABx),
    SETUPVAL(LuaOpcodeType.ABC),
    SETTABLE(LuaOpcodeType.ABC),
    NEWTABLE(LuaOpcodeType.ABC),
    SELF(LuaOpcodeType.ABC),
    ADD(LuaOpcodeType.ABC),
    SUB(LuaOpcodeType.ABC),
    MUL(LuaOpcodeType.ABC),
    DIV(LuaOpcodeType.ABC),
    MOD(LuaOpcodeType.ABC),
    POW(LuaOpcodeType.ABC),
    UNM(LuaOpcodeType.ABC),
    NOT(LuaOpcodeType.ABC),
    LEN(LuaOpcodeType.ABC),
    CONCAT(LuaOpcodeType.ABC),
    JMP(LuaOpcodeType.AsBx),
    EQ(LuaOpcodeType.ABC),
    LT(LuaOpcodeType.ABC),
    LE(LuaOpcodeType.ABC),
    TEST(LuaOpcodeType.ABC),
    TESTSET(LuaOpcodeType.ABC),
    CALL(LuaOpcodeType.ABC),
    TAILCALL(LuaOpcodeType.ABC),
    RETURN(LuaOpcodeType.ABC),
    FORLOOP(LuaOpcodeType.AsBx),
    FORPREP(LuaOpcodeType.AsBx),
    TFORLOOP(LuaOpcodeType.ABC),
    SETLIST(LuaOpcodeType.ABC),
    CLOSE(LuaOpcodeType.ABC),
    CLOSURE(LuaOpcodeType.ABx),
    VARARG(LuaOpcodeType.ABC)
}